pyeasycalc/__init__.py
pyeasycalc/pyeasycalc.py
pyeasycalc-0.2.4.dist-info/licenses/LICENSE
pyeasycalc-0.2.4.dist-info/METADATA
pyeasycalc-0.2.4.dist-info/WHEEL
pyeasycalc-0.2.4.dist-info/top_level.txt
pyeasycalc-0.2.4.dist-info/RECORD
