Metadata-Version: 2.4
Name: pyeasycalc
Version: 0.2.4
Summary: A simple and easy-to-use math utility library for Python
Author: aadidev11
Requires-Python: >=3.6
License-File: LICENSE
Dynamic: author
Dynamic: license-file
Dynamic: requires-python
Dynamic: summary
